lazy_freeze/__init__.py
lazy_freeze/decorator.py
lazy_freeze-0.1.0.dist-info/licenses/LICENSE
lazy_freeze-0.1.0.dist-info/METADATA
lazy_freeze-0.1.0.dist-info/WHEEL
lazy_freeze-0.1.0.dist-info/top_level.txt
lazy_freeze-0.1.0.dist-info/RECORD
