Metadata-Version: 2.4
Name: lazy-freeze
Version: 0.1.0
Summary: A decorator that makes objects immutable after their hash is calculated
Author-email: Ofek Shilon <ofekshilon@gmail.com>
License: MIT License
Project-URL: Homepage, https://github.com/ofekshilon/lazy-freeze
Project-URL: Bug Tracker, https://github.com/ofekshilon/lazy-freeze/issues
Keywords: hash,immutable,dictionary,frozen,decorator
Classifier: Programming Language :: Python :: 3
Classifier: Programming Language :: Python :: 3.7
Classifier: Programming Language :: Python :: 3.8
Classifier: Programming Language :: Python :: 3.9
Classifier: Programming Language :: Python :: 3.10
Classifier: Programming Language :: Python :: 3.11
Classifier: License :: OSI Approved :: MIT License
Classifier: Operating System :: OS Independent
Classifier: Topic :: Software Development :: Libraries :: Python Modules
Classifier: Intended Audience :: Developers
Requires-Python: >=3.7
License-File: LICENSE
Dynamic: license-file
